python_script_manager/__init__.py
python_script_manager/__main__.py
python_script_manager/const.py
python_script_manager/funcs.py
python_script_manager/globals.py
python_script_manager/basic/__init__.py
python_script_manager/basic/commands.py
python_script_manager/basic/funcs.py
python_script_manager/basis/__init__.py
python_script_manager/basis/commands.py
python_script_manager/basis/funcs.py
python_script_manager/environment/__init__.py
python_script_manager/environment/commands.py
python_script_manager/environment/funcs.py
python_script_manager/get/__init__.py
python_script_manager/get/commands.py
python_script_manager/package/__init__.py
python_script_manager/package/reader.py
python_script_manager/pip/__init__.py
python_script_manager/pip/commands.py
python_script_manager/pip/funcs.py
python_script_manager/scripts/__init__.py
python_script_manager/scripts/commands.py
python_script_manager/scripts/funcs.py
python_script_manager/templates/__init__.py
python_script_manager/templates/blank.py
python_script_manager/templates/django.py
python_script_manager/templates/flaskmng.py
python_script_manager/templates/pypi.py
python_script_manager-1.3.3.dist-info/LICENSE.txt
python_script_manager-1.3.3.dist-info/METADATA
python_script_manager-1.3.3.dist-info/WHEEL
python_script_manager-1.3.3.dist-info/top_level.txt
python_script_manager-1.3.3.dist-info/RECORD
